{"ts":500,"kind":"file","effect":"file_read","action":"Unknown","pid":4904,"procid":82,"srcpath":"C:\\Windows","dstpath":""}
{"ts":500,"kind":"file","effect":"file_read","action":"open_read","pid":4904,"procid":82,"srcpath":"C:\\Windows","dstpath":""}
{"ts":500,"kind":"file","effect":"file_read","action":"Unknown","pid":4904,"procid":82,"srcpath":"C:\\Users\\ADMINI~1\\AppData\\Local\\Temp\\","dstpath":""}
{"ts":531,"kind":"file","effect":"file_read","action":"open_read","pid":4904,"procid":82,"srcpath":"C:\\Users\\ADMINI~1\\AppData\\Local\\Temp\\VirusShare_de1d9d35a790080138c0aa5efd78ac2c.exe","dstpath":""}
{"ts":531,"kind":"file","effect":"file_read","action":"open_read","pid":4904,"procid":82,"srcpath":"C:\\Users\\ADMINI~1\\AppData\\Local\\Temp\\VirusShare_de1d9d35a790080138c0aa5efd78ac2c.exe","dstpath":""}
{"ts":531,"kind":"file","effect":"file_read","action":"Unknown","pid":4904,"procid":82,"srcpath":"\\??\\C:\\","dstpath":""}
{"ts":531,"kind":"file","effect":"file_read","action":"Unknown","pid":4904,"procid":82,"srcpath":"C:\\Users\\","dstpath":""}
{"ts":531,"kind":"file","effect":"file_read","action":"Unknown","pid":4904,"procid":82,"srcpath":"C:\\Users\\ADMINI~1\\","dstpath":""}
{"ts":531,"kind":"file","effect":"file_read","action":"Unknown","pid":4904,"procid":82,"srcpath":"C:\\Users\\ADMINI~1\\AppData\\","dstpath":""}
{"ts":531,"kind":"file","effect":"file_read","action":"Unknown","pid":4904,"procid":82,"srcpath":"C:\\Users\\ADMINI~1\\AppData\\Local\\","dstpath":""}
{"ts":531,"kind":"file","effect":"file_read","action":"open_read","pid":4904,"procid":82,"srcpath":"C:\\Users\\ADMINI~1\\AppData\\Local\\Temp\\VirusShare_de1d9d35a790080138c0aa5efd78ac2c.exe","dstpath":""}
{"ts":531,"kind":"file","effect":"file_read","action":"Unknown","pid":4904,"procid":82,"srcpath":"\\??\\C:\\","dstpath":""}
{"ts":531,"kind":"file","effect":"file_read","action":"Unknown","pid":4904,"procid":82,"srcpath":"C:\\Users\\","dstpath":""}
{"ts":531,"kind":"file","effect":"file_read","action":"Unknown","pid":4904,"procid":82,"srcpath":"C:\\Users\\ADMINI~1\\","dstpath":""}
{"ts":531,"kind":"file","effect":"file_read","action":"Unknown","pid":4904,"procid":82,"srcpath":"C:\\Users\\ADMINI~1\\AppData\\","dstpath":""}
{"ts":531,"kind":"file","effect":"file_read","action":"Unknown","pid":4904,"procid":82,"srcpath":"C:\\Users\\ADMINI~1\\AppData\\Local\\","dstpath":""}
{"ts":609,"kind":"file","effect":"file_read","action":"open_read","pid":4904,"procid":82,"srcpath":"C:\\Users\\ADMINI~1\\AppData\\Local\\Temp\\VirusShare_de1d9d35a790080138c0aa5efd78ac2c.exe","dstpath":""}
{"ts":609,"kind":"file","effect":"file_read","action":"Unknown","pid":4904,"procid":82,"srcpath":"\\??\\C:\\","dstpath":""}
{"ts":609,"kind":"file","effect":"file_read","action":"Unknown","pid":4904,"procid":82,"srcpath":"C:\\Users\\","dstpath":""}
{"ts":609,"kind":"file","effect":"file_read","action":"Unknown","pid":4904,"procid":82,"srcpath":"C:\\Users\\ADMINI~1\\","dstpath":""}
{"ts":609,"kind":"file","effect":"file_read","action":"Unknown","pid":4904,"procid":82,"srcpath":"C:\\Users\\ADMINI~1\\AppData\\","dstpath":""}
{"ts":609,"kind":"file","effect":"file_read","action":"Unknown","pid":4904,"procid":82,"srcpath":"C:\\Users\\ADMINI~1\\AppData\\Local\\","dstpath":""}
{"ts":625,"kind":"file","effect":"file_read","action":"Unknown","pid":4904,"procid":82,"srcpath":"C:\\Windows\\WinSxS\\x86_microsoft.windows.common-controls_6595b64144ccf1df_6.0.15063.0_none_583b8639f462029f","dstpath":""}
{"ts":718,"kind":"file","effect":"file_read","action":"open_read","pid":4904,"procid":82,"srcpath":"\\Device\\DeviceApi\\CMApi","dstpath":""}
{"ts":718,"kind":"file","effect":"file_read","action":"open_read","pid":4904,"procid":82,"srcpath":"\\Device\\CNG","dstpath":""}
{"ts":750,"kind":"file","effect":"file_read","action":"open_read","pid":4904,"procid":82,"srcpath":"\\??\\C:","dstpath":""}
{"ts":750,"kind":"file","effect":"file_read","action":"open_read","pid":4904,"procid":82,"srcpath":"\\??\\MountPointManager","dstpath":""}
{"ts":750,"kind":"file","effect":"file_read","action":"open_read","pid":4904,"procid":82,"srcpath":"\\??\\C:\\","dstpath":""}
{"ts":750,"kind":"file","effect":"file_read","action":"Unknown","pid":4904,"procid":82,"srcpath":"C:\\Users\\Administrator\\AppData\\Local\\Microsoft\\Windows\\Caches","dstpath":""}
{"ts":750,"kind":"file","effect":"file_read","action":"open_read","pid":4904,"procid":82,"srcpath":"C:\\Users\\Administrator\\AppData\\Local\\Microsoft\\Windows\\Caches","dstpath":""}
{"ts":750,"kind":"file","effect":"file_read","action":"open_read","pid":4904,"procid":82,"srcpath":"C:\\Users\\Administrator\\AppData\\Local\\Microsoft\\Windows\\Caches","dstpath":""}
{"ts":750,"kind":"file","effect":"file_read","action":"open_read","pid":4904,"procid":82,"srcpath":"C:\\Users\\Administrator\\AppData\\Local\\Microsoft\\Windows\\Caches\\cversions.1.db","dstpath":""}
{"ts":750,"kind":"file","effect":"file_read","action":"open_read","pid":4904,"procid":82,"srcpath":"C:\\Users\\Administrator\\AppData\\Local\\Microsoft\\Windows\\Caches\\{AFBF9F1A-8EE8-4C77-AF34-C647E37CA0D9}.1.ver0x0000000000000001.db","dstpath":""}
{"ts":750,"kind":"file","effect":"file_read","action":"open_read","pid":4904,"procid":82,"srcpath":"C:\\Users\\desktop.ini","dstpath":""}
{"ts":765,"kind":"file","effect":"file_read","action":"open_read","pid":4904,"procid":82,"srcpath":"C:\\Users","dstpath":""}
{"ts":765,"kind":"file","effect":"file_read","action":"open_read","pid":4904,"procid":82,"srcpath":"C:\\Users\\Administrator","dstpath":""}
{"ts":765,"kind":"file","effect":"file_read","action":"open_read","pid":4904,"procid":82,"srcpath":"C:\\Users\\Administrator\\AppData","dstpath":""}
{"ts":765,"kind":"file","effect":"file_read","action":"open_read","pid":4904,"procid":82,"srcpath":"C:\\Users\\Administrator\\AppData\\Local","dstpath":""}
{"ts":765,"kind":"file","effect":"file_read","action":"open_read","pid":4904,"procid":82,"srcpath":"C:\\Users\\Administrator\\Desktop\\desktop.ini","dstpath":""}
{"ts":765,"kind":"file","effect":"file_read","action":"open_read","pid":4904,"procid":82,"srcpath":"C:\\Users\\Administrator\\Documents\\desktop.ini","dstpath":""}
{"ts":765,"kind":"file","effect":"file_read","action":"open_read","pid":4904,"procid":82,"srcpath":"C:\\Users\\Administrator\\Music\\desktop.ini","dstpath":""}
{"ts":765,"kind":"file","effect":"file_read","action":"open_read","pid":4904,"procid":82,"srcpath":"C:\\Users\\Administrator\\Pictures\\desktop.ini","dstpath":""}
{"ts":765,"kind":"file","effect":"file_read","action":"open_read","pid":4904,"procid":82,"srcpath":"C:\\Users\\Administrator\\Videos\\desktop.ini","dstpath":""}
{"ts":765,"kind":"file","effect":"file_read","action":"open_read","pid":4904,"procid":82,"srcpath":"C:\\Users\\Administrator\\Downloads\\desktop.ini","dstpath":""}
{"ts":765,"kind":"file","effect":"file_read","action":"open_read","pid":4904,"procid":82,"srcpath":"C:\\Users\\Administrator\\OneDrive\\desktop.ini","dstpath":""}
{"ts":765,"kind":"file","effect":"file_read","action":"open_read","pid":4904,"procid":82,"srcpath":"C:\\Users\\Administrator\\OneDrive\\desktop.ini","dstpath":""}
{"ts":796,"kind":"file","effect":"file_read","action":"open_read","pid":4904,"procid":82,"srcpath":"C:\\Users\\Administrator\\Searches\\desktop.ini","dstpath":""}
{"ts":796,"kind":"file","effect":"file_read","action":"open_read","pid":4904,"procid":82,"srcpath":"C:\\Users\\Administrator\\Contacts\\desktop.ini","dstpath":""}
{"ts":796,"kind":"file","effect":"file_read","action":"open_read","pid":4904,"procid":82,"srcpath":"C:\\Users\\Administrator\\Favorites\\desktop.ini","dstpath":""}
{"ts":796,"kind":"file","effect":"file_read","action":"open_read","pid":4904,"procid":82,"srcpath":"C:\\Users\\Administrator\\Links\\desktop.ini","dstpath":""}
{"ts":796,"kind":"file","effect":"file_read","action":"open_read","pid":4904,"procid":82,"srcpath":"C:\\Users\\Administrator\\Saved Games\\desktop.ini","dstpath":""}
{"ts":796,"kind":"file","effect":"file_read","action":"open_read","pid":4904,"procid":82,"srcpath":"\\??\\STORAGE#Volume#{acbf57f0-c3bf-11ef-a098-806e6f6e6963}#0000000012D00000#{53f5630d-b6bf-11d0-94f2-00a0c91efb8b}","dstpath":""}
{"ts":796,"kind":"file","effect":"file_read","action":"open_read","pid":4904,"procid":82,"srcpath":"\\??\\STORAGE#Volume#{acbf57f0-c3bf-11ef-a098-806e6f6e6963}#0000000012D00000#{53f5630d-b6bf-11d0-94f2-00a0c91efb8b}","dstpath":""}
{"ts":796,"kind":"file","effect":"file_read","action":"open_read","pid":4904,"procid":82,"srcpath":"\\??\\MountPointManager","dstpath":""}
{"ts":796,"kind":"file","effect":"file_read","action":"open_read","pid":4904,"procid":82,"srcpath":"\\??\\SCSI#CdRom&Ven_QEMU&Prod_QEMU_DVD-ROM#4&215468a5&0&010000#{53f5630d-b6bf-11d0-94f2-00a0c91efb8b}","dstpath":""}
{"ts":796,"kind":"file","effect":"file_read","action":"open_read","pid":4904,"procid":82,"srcpath":"\\??\\SCSI#CdRom&Ven_QEMU&Prod_QEMU_DVD-ROM#4&215468a5&0&010000#{53f5630d-b6bf-11d0-94f2-00a0c91efb8b}","dstpath":""}
{"ts":796,"kind":"file","effect":"file_read","action":"open_read","pid":4904,"procid":82,"srcpath":"\\??\\MountPointManager","dstpath":""}
{"ts":796,"kind":"file","effect":"file_read","action":"open_read","pid":4904,"procid":82,"srcpath":"\\??\\STORAGE#Volume#{acbf57f0-c3bf-11ef-a098-806e6f6e6963}#0000000000100000#{53f5630d-b6bf-11d0-94f2-00a0c91efb8b}","dstpath":""}
{"ts":812,"kind":"file","effect":"file_read","action":"open_read","pid":4904,"procid":82,"srcpath":"\\??\\STORAGE#Volume#{acbf57f0-c3bf-11ef-a098-806e6f6e6963}#0000000000100000#{53f5630d-b6bf-11d0-94f2-00a0c91efb8b}","dstpath":""}
{"ts":812,"kind":"file","effect":"file_read","action":"open_read","pid":4904,"procid":82,"srcpath":"\\??\\MountPointManager","dstpath":""}
{"ts":812,"kind":"file","effect":"file_read","action":"open_read","pid":4904,"procid":82,"srcpath":"\\??\\MountPointManager","dstpath":""}
{"ts":812,"kind":"file","effect":"file_read","action":"open_read","pid":4904,"procid":82,"srcpath":"\\??\\MountPointManager","dstpath":""}
{"ts":812,"kind":"file","effect":"file_read","action":"open_read","pid":4904,"procid":82,"srcpath":"\\??\\MountPointManager","dstpath":""}
{"ts":812,"kind":"file","effect":"file_read","action":"open_read","pid":4904,"procid":82,"srcpath":"\\??\\C:","dstpath":""}
{"ts":812,"kind":"file","effect":"file_read","action":"open_read","pid":4904,"procid":82,"srcpath":"\\??\\MountPointManager","dstpath":""}
{"ts":812,"kind":"file","effect":"file_read","action":"open_read","pid":4904,"procid":82,"srcpath":"\\??\\MountPointManager","dstpath":""}
{"ts":812,"kind":"file","effect":"file_read","action":"open_read","pid":4904,"procid":82,"srcpath":"\\??\\MountPointManager","dstpath":""}
{"ts":812,"kind":"file","effect":"file_read","action":"open_read","pid":4904,"procid":82,"srcpath":"\\??\\MountPointManager","dstpath":""}
{"ts":812,"kind":"file","effect":"file_read","action":"open_read","pid":4904,"procid":82,"srcpath":"\\??\\C:\\","dstpath":""}
{"ts":812,"kind":"file","effect":"file_read","action":"open_read","pid":4904,"procid":82,"srcpath":"C:\\Users","dstpath":""}
{"ts":828,"kind":"file","effect":"file_read","action":"Unknown","pid":4904,"procid":82,"srcpath":"C:\\Users\\ADMINI~1\\AppData\\Local\\Temp\\","dstpath":""}
{"ts":859,"kind":"file","effect":"file_created","action":"create_read","pid":4904,"procid":82,"srcpath":"C:\\Users\\ADMINI~1\\AppData\\Local\\Temp\\nsl413F.tmp","dstpath":""}
{"ts":859,"kind":"file","effect":"file_read","action":"open_read","pid":4904,"procid":82,"srcpath":"C:\\Users\\ADMINI~1\\AppData\\Local\\Temp\\nsl413F.tmp","dstpath":""}
{"ts":859,"kind":"file","effect":"file_deleted","action":"delete","pid":4904,"procid":82,"srcpath":"C:\\Users\\ADMINI~1\\AppData\\Local\\Temp\\nsl413F.tmp","dstpath":""}
{"ts":859,"kind":"file","effect":"file_read","action":"open_read","pid":4904,"procid":82,"srcpath":"C:\\Users\\ADMINI~1\\AppData\\Local\\Temp\\VirusShare_de1d9d35a790080138c0aa5efd78ac2c.exe","dstpath":""}
{"ts":859,"kind":"file","effect":"file_created","action":"create_read","pid":4904,"procid":82,"srcpath":"C:\\Users\\ADMINI~1\\AppData\\Local\\Temp\\nsq415F.tmp","dstpath":""}
{"ts":859,"kind":"file","effect":"file_read","action":"Unknown","pid":4904,"procid":82,"srcpath":"C:\\Users\\ADMINI~1\\AppData\\Local\\Temp\\","dstpath":""}
{"ts":859,"kind":"file","effect":"file_read","action":"open_read","pid":4904,"procid":82,"srcpath":"C:\\Users\\ADMINI~1\\AppData\\Local\\Temp\\nsq415F.tmp","dstpath":""}
{"ts":859,"kind":"file","effect":"file_deleted","action":"delete","pid":4904,"procid":82,"srcpath":"C:\\Users\\ADMINI~1\\AppData\\Local\\Temp\\nsq415F.tmp","dstpath":""}
{"ts":859,"kind":"file","effect":"file_read","action":"Unknown","pid":4904,"procid":82,"srcpath":"C:\\Users","dstpath":""}
{"ts":859,"kind":"file","effect":"file_read","action":"Unknown","pid":4904,"procid":82,"srcpath":"C:\\Users\\ADMINI~1","dstpath":""}
{"ts":859,"kind":"file","effect":"file_read","action":"Unknown","pid":4904,"procid":82,"srcpath":"C:\\Users\\ADMINI~1\\AppData","dstpath":""}
{"ts":859,"kind":"file","effect":"file_read","action":"Unknown","pid":4904,"procid":82,"srcpath":"C:\\Users\\ADMINI~1\\AppData\\Local","dstpath":""}
{"ts":859,"kind":"file","effect":"file_read","action":"Unknown","pid":4904,"procid":82,"srcpath":"C:\\Users\\ADMINI~1\\AppData\\Local\\Temp","dstpath":""}
{"ts":859,"kind":"file","effect":"file_read","action":"Unknown","pid":4904,"procid":82,"srcpath":"C:\\Users\\ADMINI~1\\AppData\\Local\\Temp\\nsq415F.tmp","dstpath":""}
{"ts":859,"kind":"file","effect":"file_created","action":"create_modify","pid":4904,"procid":82,"srcpath":"C:\\Users\\ADMINI~1\\AppData\\Local\\Temp\\nsq415F.tmp\\aminsis.dll","dstpath":""}
{"ts":875,"kind":"file","effect":"file_read","action":"open_read","pid":4904,"procid":82,"srcpath":"C:\\Users\\ADMINI~1\\AppData\\Local\\Temp\\nsq415F.tmp\\aminsis.dll","dstpath":""}
{"ts":875,"kind":"file","effect":"file_read","action":"open_read","pid":4904,"procid":82,"srcpath":"C:\\Users\\ADMINI~1\\AppData\\Local\\Temp\\nsq415F.tmp\\aminsis.dll","dstpath":""}
{"ts":906,"kind":"file","effect":"file_read","action":"open_read","pid":4904,"procid":82,"srcpath":"C:\\Users\\ADMINI~1\\AppData\\Local\\Temp\\nsq415F.tmp\\aminsis.dll","dstpath":""}
{"ts":906,"kind":"file","effect":"file_read","action":"open_read","pid":4904,"procid":82,"srcpath":"C:\\Users\\ADMINI~1\\AppData\\Local\\Temp\\nsq415F.tmp\\aminsis.dll","dstpath":""}
{"ts":906,"kind":"file","effect":"file_read","action":"Unknown","pid":4904,"procid":82,"srcpath":"C:\\Users\\ADMINI~1\\AppData\\Local\\Temp\\","dstpath":""}
{"ts":906,"kind":"file","effect":"file_created","action":"create_modify","pid":4904,"procid":82,"srcpath":"C:\\Users\\ADMINI~1\\AppData\\Local\\Temp\\aminsis.txt","dstpath":""}
{"ts":906,"kind":"file","effect":"file_read","action":"Unknown","pid":4904,"procid":82,"srcpath":"C:\\Users\\Administrator\\AppData\\Local\\Google\\Chrome\\Application\\","dstpath":""}
{"ts":906,"kind":"file","effect":"file_read","action":"open_read","pid":4904,"procid":82,"srcpath":"C:\\Users\\Administrator\\AppData\\Local\\Google\\Chrome\\User Data\\Local State","dstpath":""}
{"ts":906,"kind":"file","effect":"file_read","action":"Unknown","pid":4904,"procid":82,"srcpath":"C:\\Users\\Administrator\\AppData\\Local\\Google\\Chrome\\User Data\\Default\\","dstpath":""}
{"ts":906,"kind":"file","effect":"file_read","action":"open_read","pid":4904,"procid":82,"srcpath":"C:\\Users\\Administrator\\AppData\\Roaming\\Mozilla\\Firefox\\profiles.ini","dstpath":""}
{"ts":906,"kind":"file","effect":"file_read","action":"open_read","pid":4904,"procid":82,"srcpath":"C:\\Users\\Administrator\\AppData\\Roaming\\Mozilla\\Firefox\\profiles.ini","dstpath":""}
{"ts":906,"kind":"file","effect":"file_read","action":"Unknown","pid":4904,"procid":82,"srcpath":"\\??\\C:\\","dstpath":""}
{"ts":906,"kind":"file","effect":"file_created","action":"create_modify","pid":4904,"procid":82,"srcpath":"C:\\Users\\ADMINI~1\\AppData\\Local\\Temp\\nsq415F.tmp\\aminsis.dll","dstpath":""}
{"ts":937,"kind":"file","effect":"file_written","action":"open_modify","pid":4904,"procid":82,"srcpath":"\\Device\\KsecDD","dstpath":""}
{"ts":1234,"kind":"file","effect":"file_read","action":"Unknown","pid":4904,"procid":82,"srcpath":"C:\\Users\\ADMINI~1\\AppData\\Local\\Temp\\","dstpath":""}
{"ts":1234,"kind":"file","effect":"file_read","action":"Unknown","pid":4904,"procid":82,"srcpath":"C:\\Users\\ADMINI~1\\AppData\\Local\\","dstpath":""}
{"ts":1234,"kind":"file","effect":"file_read","action":"Unknown","pid":4904,"procid":82,"srcpath":"C:\\Users\\ADMINI~1\\AppData\\","dstpath":""}
{"ts":1234,"kind":"file","effect":"file_read","action":"Unknown","pid":4904,"procid":82,"srcpath":"C:\\Users\\ADMINI~1\\","dstpath":""}
{"ts":1234,"kind":"file","effect":"file_read","action":"Unknown","pid":4904,"procid":82,"srcpath":"C:\\Users\\","dstpath":""}
{"ts":1234,"kind":"file","effect":"file_read","action":"Unknown","pid":4904,"procid":82,"srcpath":"\\??\\C:\\","dstpath":""}
{"ts":1234,"kind":"file","effect":"file_read","action":"Unknown","pid":4904,"procid":82,"srcpath":"C:\\Users\\ADMINI~1\\AppData\\Local\\Temp\\nsq415F.tmp\\","dstpath":""}
{"ts":1234,"kind":"file","effect":"file_written","action":"open_modify","pid":4904,"procid":82,"srcpath":"C:\\Users\\ADMINI~1\\AppData\\Local\\Temp\\nsq415F.tmp\\aminsis.dll","dstpath":""}
{"ts":1234,"kind":"file","effect":"file_read","action":"open_read","pid":4904,"procid":82,"srcpath":"C:\\Users\\ADMINI~1\\AppData\\Local\\Temp\\nsq415F.tmp\\aminsis.dll","dstpath":""}
{"ts":1234,"kind":"file","effect":"file_deleted","action":"delete","pid":4904,"procid":82,"srcpath":"C:\\Users\\ADMINI~1\\AppData\\Local\\Temp\\nsq415F.tmp\\aminsis.dll","dstpath":""}
{"ts":1234,"kind":"file","effect":"file_read","action":"open_read","pid":4904,"procid":82,"srcpath":"C:\\Users\\ADMINI~1\\AppData\\Local\\Temp\\nsq415F.tmp\\aminsis.dll","dstpath":""}
{"ts":1234,"kind":"file","effect":"file_read","action":"Unknown","pid":4904,"procid":82,"srcpath":"C:\\Users\\ADMINI~1\\AppData\\Local\\Temp\\","dstpath":""}
{"ts":1234,"kind":"file","effect":"file_written","action":"open_modify","pid":4904,"procid":82,"srcpath":"C:\\Users\\ADMINI~1\\AppData\\Local\\Temp\\nsq415F.tmp\\","dstpath":""}
{"ts":1234,"kind":"file","effect":"file_read","action":"Unknown","pid":4904,"procid":82,"srcpath":"C:\\Users\\ADMINI~1\\AppData\\Local\\Temp\\nsq415F.tmp\\","dstpath":""}
{"ts":1234,"kind":"file","effect":"file_deleted","action":"delete","pid":4904,"procid":82,"srcpath":"C:\\Users\\ADMINI~1\\AppData\\Local\\Temp\\nsq415F.tmp","dstpath":""}
{"ts":1234,"kind":"file","effect":"file_read","action":"open_read","pid":4904,"procid":82,"srcpath":"C:\\Users\\ADMINI~1\\AppData\\Local\\Temp\\nsq415F.tmp\\","dstpath":""}
{"ts":104140,"kind":"file","effect":"file_read","action":"Unknown","pid":976,"procid":90,"srcpath":"C:\\Windows\\system32\\","dstpath":""}
{"ts":104156,"kind":"file","effect":"file_read","action":"open_read","pid":976,"procid":90,"srcpath":"\\Device\\CNG","dstpath":""}
{"ts":104296,"kind":"file","effect":"file_read","action":"Unknown","pid":4428,"procid":91,"srcpath":"C:\\Windows\\system32\\","dstpath":""}
{"ts":104296,"kind":"file","effect":"file_read","action":"open_read","pid":4428,"procid":91,"srcpath":"\\Device\\CNG","dstpath":""}
{"ts":104500,"kind":"file","effect":"file_read","action":"open_read","pid":4428,"procid":91,"srcpath":"\\??\\Nsi","dstpath":""}
{"ts":104500,"kind":"file","effect":"file_read","action":"open_read","pid":4428,"procid":91,"srcpath":"\\DEVICE\\NETBT_TCPIP_{B6098F25-97F6-4D7D-BAE2-D21D794F77F5}","dstpath":""}
{"ts":104500,"kind":"file","effect":"file_read","action":"open_read","pid":4428,"procid":91,"srcpath":"\\DEVICE\\NETBT_TCPIP_{ACBF57ED-C3BF-11EF-A098-806E6F6E6963}","dstpath":""}
{"ts":104500,"kind":"file","effect":"file_read","action":"open_read","pid":4428,"procid":91,"srcpath":"\\DEVICE\\NETBT_TCPIP_{B6098F25-97F6-4D7D-BAE2-D21D794F77F5}","dstpath":""}
{"ts":104500,"kind":"file","effect":"file_read","action":"open_read","pid":4428,"procid":91,"srcpath":"\\DEVICE\\NETBT_TCPIP_{ACBF57ED-C3BF-11EF-A098-806E6F6E6963}","dstpath":""}
{"ts":104500,"kind":"file","effect":"file_read","action":"open_read","pid":4428,"procid":91,"srcpath":"\\DEVICE\\NETBT_TCPIP_{B6098F25-97F6-4D7D-BAE2-D21D794F77F5}","dstpath":""}
{"ts":104500,"kind":"file","effect":"file_read","action":"open_read","pid":4428,"procid":91,"srcpath":"\\DEVICE\\NETBT_TCPIP_{ACBF57ED-C3BF-11EF-A098-806E6F6E6963}","dstpath":""}
{"ts":104500,"kind":"file","effect":"file_read","action":"open_read","pid":4428,"procid":91,"srcpath":"\\DEVICE\\NETBT_TCPIP_{B6098F25-97F6-4D7D-BAE2-D21D794F77F5}","dstpath":""}
{"ts":104500,"kind":"file","effect":"file_read","action":"open_read","pid":4428,"procid":91,"srcpath":"\\DEVICE\\NETBT_TCPIP_{ACBF57ED-C3BF-11EF-A098-806E6F6E6963}","dstpath":""}
{"ts":104500,"kind":"file","effect":"file_written","action":"open_modify","pid":4428,"procid":91,"srcpath":"\\Device\\KsecDD","dstpath":""}
{"ts":104500,"kind":"file","effect":"file_written","action":"open_modify","pid":4428,"procid":91,"srcpath":"\\Device\\Afd\\Endpoint","dstpath":""}
{"ts":104500,"kind":"file","effect":"file_written","action":"open_modify","pid":4428,"procid":91,"srcpath":"\\Device\\Afd\\Endpoint","dstpath":""}
{"ts":104500,"kind":"file","effect":"file_written","action":"open_modify","pid":4428,"procid":91,"srcpath":"\\Device\\Afd\\Endpoint","dstpath":""}
{"ts":104500,"kind":"file","effect":"file_written","action":"open_modify","pid":4428,"procid":91,"srcpath":"\\Device\\Afd\\Endpoint","dstpath":""}
{"ts":104500,"kind":"file","effect":"file_written","action":"open_modify","pid":4428,"procid":91,"srcpath":"\\Device\\Afd\\Endpoint","dstpath":""}
{"ts":104500,"kind":"file","effect":"file_written","action":"open_modify","pid":4428,"procid":91,"srcpath":"\\Device\\Afd\\Endpoint","dstpath":""}
{"ts":104500,"kind":"file","effect":"file_written","action":"open_modify","pid":4428,"procid":91,"srcpath":"\\Device\\Afd\\Endpoint","dstpath":""}
{"ts":104500,"kind":"file","effect":"file_written","action":"open_modify","pid":4428,"procid":91,"srcpath":"\\Device\\Afd\\Endpoint","dstpath":""}
{"ts":104562,"kind":"file","effect":"file_written","action":"open_modify","pid":976,"procid":90,"srcpath":"C:\\ProgramData\\Microsoft\\Network\\Downloader\\qmgr0.dat","dstpath":""}
{"ts":104562,"kind":"file","effect":"file_written","action":"open_modify","pid":976,"procid":90,"srcpath":"C:\\ProgramData\\Microsoft\\Network\\Downloader\\qmgr1.dat","dstpath":""}
{"ts":104562,"kind":"file","effect":"file_read","action":"open_read","pid":976,"procid":90,"srcpath":"C:\\ProgramData\\Microsoft\\Network\\Downloader","dstpath":""}
{"ts":104562,"kind":"file","effect":"file_read","action":"open_read","pid":976,"procid":90,"srcpath":"C:\\ProgramData\\Microsoft\\Network\\Downloader\\","dstpath":""}
{"ts":104562,"kind":"file","effect":"file_read","action":"open_read","pid":976,"procid":90,"srcpath":"C:\\ProgramData\\Microsoft\\Network\\Downloader","dstpath":""}
{"ts":104562,"kind":"file","effect":"file_read","action":"open_read","pid":976,"procid":90,"srcpath":"C:\\ProgramData\\Microsoft\\Network\\Downloader","dstpath":""}
{"ts":104562,"kind":"file","effect":"file_read","action":"open_read","pid":976,"procid":90,"srcpath":"C:\\ProgramData\\Microsoft\\Network\\Downloader\\","dstpath":""}
{"ts":104562,"kind":"file","effect":"file_read","action":"open_read","pid":976,"procid":90,"srcpath":"C:\\ProgramData\\Microsoft\\Network","dstpath":""}
{"ts":104562,"kind":"file","effect":"file_read","action":"open_read","pid":976,"procid":90,"srcpath":"C:\\ProgramData\\Microsoft\\Network\\","dstpath":""}
{"ts":104562,"kind":"file","effect":"file_read","action":"open_read","pid":976,"procid":90,"srcpath":"C:\\ProgramData\\Microsoft\\Network","dstpath":""}
{"ts":104562,"kind":"file","effect":"file_read","action":"open_read","pid":976,"procid":90,"srcpath":"C:\\ProgramData\\Microsoft\\Network","dstpath":""}
{"ts":104562,"kind":"file","effect":"file_read","action":"open_read","pid":976,"procid":90,"srcpath":"C:\\ProgramData\\Microsoft\\Network\\","dstpath":""}
{"ts":104562,"kind":"file","effect":"file_read","action":"open_read","pid":976,"procid":90,"srcpath":"C:\\ProgramData\\Microsoft","dstpath":""}
{"ts":104562,"kind":"file","effect":"file_read","action":"open_read","pid":976,"procid":90,"srcpath":"C:\\ProgramData\\Microsoft\\","dstpath":""}
{"ts":104562,"kind":"file","effect":"file_read","action":"open_read","pid":976,"procid":90,"srcpath":"C:\\ProgramData\\Microsoft","dstpath":""}
{"ts":104562,"kind":"file","effect":"file_read","action":"open_read","pid":976,"procid":90,"srcpath":"C:\\ProgramData\\Microsoft","dstpath":""}
{"ts":104562,"kind":"file","effect":"file_read","action":"open_read","pid":976,"procid":90,"srcpath":"C:\\ProgramData\\Microsoft\\","dstpath":""}
{"ts":104562,"kind":"file","effect":"file_read","action":"open_read","pid":976,"procid":90,"srcpath":"C:\\ProgramData","dstpath":""}
{"ts":104562,"kind":"file","effect":"file_read","action":"open_read","pid":976,"procid":90,"srcpath":"C:\\ProgramData\\","dstpath":""}
{"ts":104562,"kind":"file","effect":"file_read","action":"open_read","pid":976,"procid":90,"srcpath":"C:\\ProgramData","dstpath":""}
{"ts":104562,"kind":"file","effect":"file_read","action":"open_read","pid":976,"procid":90,"srcpath":"C:\\ProgramData","dstpath":""}
{"ts":104562,"kind":"file","effect":"file_read","action":"open_read","pid":976,"procid":90,"srcpath":"C:\\ProgramData\\","dstpath":""}
{"ts":104562,"kind":"file","effect":"file_read","action":"open_read","pid":976,"procid":90,"srcpath":"\\??\\C:","dstpath":""}
{"ts":104562,"kind":"file","effect":"file_read","action":"open_read","pid":976,"procid":90,"srcpath":"\\??\\MountPointManager","dstpath":""}
{"ts":104562,"kind":"file","effect":"file_read","action":"open_read","pid":976,"procid":90,"srcpath":"C:\\ProgramData\\Microsoft\\Network\\Downloader\\","dstpath":""}
{"ts":104562,"kind":"file","effect":"file_written","action":"open_modify","pid":976,"procid":90,"srcpath":"C:\\ProgramData\\Microsoft\\Network\\Downloader\\edb.chk","dstpath":""}
{"ts":104562,"kind":"file","effect":"file_read","action":"open_read","pid":976,"procid":90,"srcpath":"\\??\\C:","dstpath":""}
{"ts":104562,"kind":"file","effect":"file_read","action":"open_read","pid":976,"procid":90,"srcpath":"\\??\\MountPointManager","dstpath":""}
{"ts":104562,"kind":"file","effect":"file_read","action":"open_read","pid":976,"procid":90,"srcpath":"\\??\\Volume{301fc0b2-0000-0000-0000-d01200000000}","dstpath":""}
{"ts":104578,"kind":"file","effect":"file_read","action":"open_read","pid":976,"procid":90,"srcpath":"\\??\\PhysicalDrive0","dstpath":""}
{"ts":104578,"kind":"file","effect":"file_read","action":"Unknown","pid":976,"procid":90,"srcpath":"C:\\ProgramData\\Microsoft\\Network\\Downloader\\","dstpath":""}
{"ts":104578,"kind":"file","effect":"file_written","action":"open_modify","pid":976,"procid":90,"srcpath":"C:\\ProgramData\\Microsoft\\Network\\Downloader\\edb.log","dstpath":""}
{"ts":104578,"kind":"file","effect":"file_written","action":"open_modify","pid":976,"procid":90,"srcpath":"C:\\ProgramData\\Microsoft\\Network\\Downloader\\edb.chk","dstpath":""}
{"ts":104578,"kind":"file","effect":"file_written","action":"open_modify","pid":976,"procid":90,"srcpath":"C:\\ProgramData\\Microsoft\\Network\\Downloader\\edb.log","dstpath":""}
{"ts":104578,"kind":"file","effect":"file_read","action":"open_read","pid":976,"procid":90,"srcpath":"C:\\ProgramData\\Microsoft\\Network\\Downloader\\res1.log","dstpath":""}
{"ts":104578,"kind":"file","effect":"file_read","action":"open_read","pid":976,"procid":90,"srcpath":"C:\\ProgramData\\Microsoft\\Network\\Downloader\\res2.log","dstpath":""}
{"ts":104578,"kind":"file","effect":"file_read","action":"Unknown","pid":976,"procid":90,"srcpath":"C:\\ProgramData\\Microsoft\\Network\\Downloader\\","dstpath":""}
{"ts":104578,"kind":"file","effect":"file_read","action":"Unknown","pid":976,"procid":90,"srcpath":"C:\\ProgramData\\Microsoft\\Network\\Downloader\\","dstpath":""}
{"ts":104578,"kind":"file","effect":"file_read","action":"Unknown","pid":976,"procid":90,"srcpath":"C:\\ProgramData\\Microsoft\\Network\\Downloader\\","dstpath":""}
{"ts":104578,"kind":"file","effect":"file_written","action":"open_modify","pid":976,"procid":90,"srcpath":"C:\\ProgramData\\Microsoft\\Network\\Downloader\\edb00001.log","dstpath":""}
{"ts":104578,"kind":"file","effect":"file_written","action":"open_modify","pid":976,"procid":90,"srcpath":"C:\\ProgramData\\Microsoft\\Network\\Downloader\\edb.log","dstpath":""}
{"ts":104578,"kind":"file","effect":"file_read","action":"Unknown","pid":976,"procid":90,"srcpath":"C:\\ProgramData\\Microsoft\\Network\\Downloader\\","dstpath":""}
{"ts":104578,"kind":"file","effect":"file_read","action":"Unknown","pid":976,"procid":90,"srcpath":"C:\\ProgramData\\Microsoft\\Network\\Downloader\\","dstpath":""}
{"ts":104578,"kind":"file","effect":"file_read","action":"Unknown","pid":976,"procid":90,"srcpath":"C:\\ProgramData\\Microsoft\\Network\\","dstpath":""}
{"ts":104578,"kind":"file","effect":"file_read","action":"Unknown","pid":976,"procid":90,"srcpath":"C:\\ProgramData\\Microsoft\\Network\\Downloader\\","dstpath":""}
{"ts":104578,"kind":"file","effect":"file_written","action":"open_modify","pid":976,"procid":90,"srcpath":"C:\\ProgramData\\Microsoft\\Network\\Downloader\\qmgr.db","dstpath":""}
{"ts":104578,"kind":"file","effect":"file_written","action":"open_modify","pid":976,"procid":90,"srcpath":"C:\\ProgramData\\Microsoft\\Network\\Downloader\\qmgr.db","dstpath":""}
{"ts":104578,"kind":"file","effect":"file_read","action":"Unknown","pid":976,"procid":90,"srcpath":"C:\\ProgramData\\Microsoft\\Network\\Downloader\\","dstpath":""}
{"ts":104578,"kind":"file","effect":"file_written","action":"open_modify","pid":976,"procid":90,"srcpath":"C:\\ProgramData\\Microsoft\\Network\\Downloader\\qmgr.jfm","dstpath":""}
{"ts":104578,"kind":"file","effect":"file_read","action":"open_read","pid":976,"procid":90,"srcpath":"C:\\ProgramData\\Microsoft\\Network\\Downloader\\qmgr.jfm","dstpath":""}
{"ts":104578,"kind":"file","effect":"file_read","action":"open_read","pid":976,"procid":90,"srcpath":"C:\\ProgramData\\Microsoft\\Network\\Downloader\\qmgr.jfm","dstpath":""}
{"ts":104578,"kind":"file","effect":"file_read","action":"open_read","pid":976,"procid":90,"srcpath":"C:\\ProgramData\\Microsoft\\Network\\Downloader\\qmgr.jfm","dstpath":""}
{"ts":104578,"kind":"file","effect":"file_read","action":"open_read","pid":976,"procid":90,"srcpath":"C:\\ProgramData\\Microsoft\\Network\\Downloader\\qmgr.jfm\\","dstpath":""}
{"ts":104578,"kind":"file","effect":"file_read","action":"open_read","pid":976,"procid":90,"srcpath":"C:\\ProgramData\\Microsoft\\Network\\Downloader","dstpath":""}
{"ts":104578,"kind":"file","effect":"file_read","action":"open_read","pid":976,"procid":90,"srcpath":"C:\\ProgramData\\Microsoft\\Network\\Downloader\\","dstpath":""}
{"ts":104578,"kind":"file","effect":"file_read","action":"open_read","pid":976,"procid":90,"srcpath":"C:\\ProgramData\\Microsoft\\Network\\Downloader","dstpath":""}
{"ts":104578,"kind":"file","effect":"file_read","action":"open_read","pid":976,"procid":90,"srcpath":"C:\\ProgramData\\Microsoft\\Network\\Downloader","dstpath":""}
{"ts":104578,"kind":"file","effect":"file_read","action":"open_read","pid":976,"procid":90,"srcpath":"C:\\ProgramData\\Microsoft\\Network\\Downloader\\","dstpath":""}
{"ts":104578,"kind":"file","effect":"file_read","action":"open_read","pid":976,"procid":90,"srcpath":"C:\\ProgramData\\Microsoft\\Network","dstpath":""}
{"ts":104578,"kind":"file","effect":"file_read","action":"open_read","pid":976,"procid":90,"srcpath":"C:\\ProgramData\\Microsoft\\Network\\","dstpath":""}
{"ts":104578,"kind":"file","effect":"file_read","action":"open_read","pid":976,"procid":90,"srcpath":"C:\\ProgramData\\Microsoft\\Network","dstpath":""}
{"ts":104578,"kind":"file","effect":"file_read","action":"open_read","pid":976,"procid":90,"srcpath":"C:\\ProgramData\\Microsoft\\Network","dstpath":""}
{"ts":104578,"kind":"file","effect":"file_read","action":"open_read","pid":976,"procid":90,"srcpath":"C:\\ProgramData\\Microsoft\\Network\\","dstpath":""}
{"ts":104578,"kind":"file","effect":"file_read","action":"open_read","pid":976,"procid":90,"srcpath":"C:\\ProgramData\\Microsoft","dstpath":""}
{"ts":104578,"kind":"file","effect":"file_read","action":"open_read","pid":976,"procid":90,"srcpath":"C:\\ProgramData\\Microsoft\\","dstpath":""}
{"ts":104578,"kind":"file","effect":"file_read","action":"open_read","pid":976,"procid":90,"srcpath":"C:\\ProgramData\\Microsoft","dstpath":""}
{"ts":104578,"kind":"file","effect":"file_read","action":"open_read","pid":976,"procid":90,"srcpath":"C:\\ProgramData\\Microsoft","dstpath":""}
{"ts":104578,"kind":"file","effect":"file_read","action":"open_read","pid":976,"procid":90,"srcpath":"C:\\ProgramData\\Microsoft\\","dstpath":""}
{"ts":104578,"kind":"file","effect":"file_read","action":"open_read","pid":976,"procid":90,"srcpath":"C:\\ProgramData","dstpath":""}
{"ts":104578,"kind":"file","effect":"file_read","action":"open_read","pid":976,"procid":90,"srcpath":"C:\\ProgramData\\","dstpath":""}
{"ts":104578,"kind":"file","effect":"file_read","action":"open_read","pid":976,"procid":90,"srcpath":"C:\\ProgramData","dstpath":""}
{"ts":104578,"kind":"file","effect":"file_read","action":"open_read","pid":976,"procid":90,"srcpath":"C:\\ProgramData","dstpath":""}
{"ts":104578,"kind":"file","effect":"file_read","action":"open_read","pid":976,"procid":90,"srcpath":"C:\\ProgramData\\","dstpath":""}
{"ts":104578,"kind":"file","effect":"file_read","action":"open_read","pid":976,"procid":90,"srcpath":"\\??\\C:","dstpath":""}
{"ts":104578,"kind":"file","effect":"file_read","action":"open_read","pid":976,"procid":90,"srcpath":"\\??\\MountPointManager","dstpath":""}
{"ts":104578,"kind":"file","effect":"file_read","action":"open_read","pid":976,"procid":90,"srcpath":"\\??\\C:","dstpath":""}
{"ts":104578,"kind":"file","effect":"file_read","action":"open_read","pid":976,"procid":90,"srcpath":"\\??\\MountPointManager","dstpath":""}
{"ts":104578,"kind":"file","effect":"file_read","action":"open_read","pid":976,"procid":90,"srcpath":"\\??\\Volume{301fc0b2-0000-0000-0000-d01200000000}","dstpath":""}
{"ts":104578,"kind":"file","effect":"file_read","action":"open_read","pid":976,"procid":90,"srcpath":"\\??\\PhysicalDrive0","dstpath":""}
{"ts":104578,"kind":"file","effect":"file_read","action":"open_read","pid":976,"procid":90,"srcpath":"C:\\ProgramData\\Microsoft\\Network\\Downloader\\qmgr.jfm","dstpath":""}
{"ts":104593,"kind":"file","effect":"file_written","action":"open_modify","pid":976,"procid":90,"srcpath":"C:\\ProgramData\\Microsoft\\Network\\Downloader\\qmgr.db","dstpath":""}
{"ts":104593,"kind":"file","effect":"file_written","action":"open_modify","pid":976,"procid":90,"srcpath":"C:\\ProgramData\\Microsoft\\Network\\Downloader\\qmgr.db","dstpath":""}
{"ts":104593,"kind":"file","effect":"file_written","action":"open_modify","pid":976,"procid":90,"srcpath":"C:\\ProgramData\\Microsoft\\Network\\Downloader\\edb.log","dstpath":""}
{"ts":104609,"kind":"file","effect":"file_read","action":"open_read","pid":976,"procid":90,"srcpath":"C:\\Windows","dstpath":""}
{"ts":104609,"kind":"file","effect":"file_read","action":"open_read","pid":976,"procid":90,"srcpath":"C:\\Windows","dstpath":""}
{"ts":104609,"kind":"file","effect":"file_read","action":"open_read","pid":976,"procid":90,"srcpath":"C:\\Windows","dstpath":""}
{"ts":104609,"kind":"file","effect":"file_read","action":"open_read","pid":976,"procid":90,"srcpath":"\\??\\C:","dstpath":""}
{"ts":104609,"kind":"file","effect":"file_read","action":"open_read","pid":976,"procid":90,"srcpath":"\\??\\MountPointManager","dstpath":""}
{"ts":104609,"kind":"file","effect":"file_read","action":"open_read","pid":976,"procid":90,"srcpath":"\\??\\C:","dstpath":""}
{"ts":104609,"kind":"file","effect":"file_read","action":"open_read","pid":976,"procid":90,"srcpath":"\\??\\MountPointManager","dstpath":""}
{"ts":104609,"kind":"file","effect":"file_read","action":"open_read","pid":976,"procid":90,"srcpath":"\\??\\Volume{301fc0b2-0000-0000-0000-d01200000000}","dstpath":""}
{"ts":104609,"kind":"file","effect":"file_read","action":"open_read","pid":976,"procid":90,"srcpath":"\\??\\PhysicalDrive0","dstpath":""}
{"ts":104625,"kind":"file","effect":"file_written","action":"open_modify","pid":976,"procid":90,"srcpath":"C:\\ProgramData\\Microsoft\\Network\\Downloader\\edb.chk","dstpath":""}
{"ts":104640,"kind":"file","effect":"file_written","action":"open_modify","pid":976,"procid":90,"srcpath":"C:\\ProgramData\\Microsoft\\Network\\Downloader\\edb.chk","dstpath":""}
{"ts":104656,"kind":"file","effect":"file_written","action":"open_modify","pid":976,"procid":90,"srcpath":"C:\\ProgramData\\Microsoft\\Network\\Downloader\\edb.chk","dstpath":""}
{"ts":104671,"kind":"file","effect":"file_written","action":"open_modify","pid":976,"procid":90,"srcpath":"C:\\ProgramData\\Microsoft\\Network\\Downloader\\edb.log","dstpath":""}
{"ts":104687,"kind":"file","effect":"file_written","action":"open_modify","pid":976,"procid":90,"srcpath":"C:\\ProgramData\\Microsoft\\Network\\Downloader\\edb.log","dstpath":""}
{"ts":104687,"kind":"file","effect":"file_written","action":"open_modify","pid":976,"procid":90,"srcpath":"C:\\ProgramData\\Microsoft\\Network\\Downloader\\edb.log","dstpath":""}
{"ts":104687,"kind":"file","effect":"file_read","action":"open_read","pid":976,"procid":90,"srcpath":"C:\\ProgramData\\Microsoft\\Network\\Downloader\\edb.chk","dstpath":""}
{"ts":104687,"kind":"file","effect":"file_read","action":"Unknown","pid":976,"procid":90,"srcpath":"C:\\ProgramData\\Microsoft\\Network\\Downloader\\","dstpath":""}
{"ts":104703,"kind":"file","effect":"file_read","action":"Unknown","pid":976,"procid":90,"srcpath":"C:\\ProgramData\\Microsoft\\Network\\Downloader\\","dstpath":""}
{"ts":104703,"kind":"file","effect":"file_written","action":"open_modify","pid":976,"procid":90,"srcpath":"C:\\ProgramData\\Microsoft\\Network\\Downloader\\qmgr.db","dstpath":""}
{"ts":104703,"kind":"file","effect":"file_read","action":"Unknown","pid":976,"procid":90,"srcpath":"C:\\ProgramData\\Microsoft\\Network\\Downloader\\","dstpath":""}
{"ts":104703,"kind":"file","effect":"file_written","action":"open_modify","pid":976,"procid":90,"srcpath":"C:\\ProgramData\\Microsoft\\Network\\Downloader\\qmgr.jfm","dstpath":""}
{"ts":104703,"kind":"file","effect":"file_read","action":"open_read","pid":976,"procid":90,"srcpath":"C:\\ProgramData\\Microsoft\\Network\\Downloader\\qmgr.jfm","dstpath":""}
{"ts":104703,"kind":"file","effect":"file_read","action":"open_read","pid":976,"procid":90,"srcpath":"C:\\ProgramData\\Microsoft\\Network\\Downloader\\qmgr.jfm","dstpath":""}
{"ts":104703,"kind":"file","effect":"file_read","action":"open_read","pid":976,"procid":90,"srcpath":"C:\\ProgramData\\Microsoft\\Network\\Downloader\\qmgr.jfm","dstpath":""}
{"ts":104703,"kind":"file","effect":"file_read","action":"open_read","pid":976,"procid":90,"srcpath":"C:\\ProgramData\\Microsoft\\Network\\Downloader\\qmgr.jfm\\","dstpath":""}
{"ts":104703,"kind":"file","effect":"file_read","action":"open_read","pid":976,"procid":90,"srcpath":"C:\\ProgramData\\Microsoft\\Network\\Downloader","dstpath":""}
{"ts":104703,"kind":"file","effect":"file_read","action":"open_read","pid":976,"procid":90,"srcpath":"C:\\ProgramData\\Microsoft\\Network\\Downloader\\","dstpath":""}
{"ts":104703,"kind":"file","effect":"file_read","action":"open_read","pid":976,"procid":90,"srcpath":"C:\\ProgramData\\Microsoft\\Network\\Downloader","dstpath":""}
{"ts":104703,"kind":"file","effect":"file_read","action":"open_read","pid":976,"procid":90,"srcpath":"C:\\ProgramData\\Microsoft\\Network\\Downloader","dstpath":""}
{"ts":104703,"kind":"file","effect":"file_read","action":"open_read","pid":976,"procid":90,"srcpath":"C:\\ProgramData\\Microsoft\\Network\\Downloader\\","dstpath":""}
{"ts":104703,"kind":"file","effect":"file_read","action":"open_read","pid":976,"procid":90,"srcpath":"C:\\ProgramData\\Microsoft\\Network","dstpath":""}
{"ts":104703,"kind":"file","effect":"file_read","action":"open_read","pid":976,"procid":90,"srcpath":"C:\\ProgramData\\Microsoft\\Network\\","dstpath":""}
{"ts":104703,"kind":"file","effect":"file_read","action":"open_read","pid":976,"procid":90,"srcpath":"C:\\ProgramData\\Microsoft\\Network","dstpath":""}
{"ts":104703,"kind":"file","effect":"file_read","action":"open_read","pid":976,"procid":90,"srcpath":"C:\\ProgramData\\Microsoft\\Network","dstpath":""}
{"ts":104703,"kind":"file","effect":"file_read","action":"open_read","pid":976,"procid":90,"srcpath":"C:\\ProgramData\\Microsoft\\Network\\","dstpath":""}
{"ts":104703,"kind":"file","effect":"file_read","action":"open_read","pid":976,"procid":90,"srcpath":"C:\\ProgramData\\Microsoft","dstpath":""}
{"ts":104703,"kind":"file","effect":"file_read","action":"open_read","pid":976,"procid":90,"srcpath":"C:\\ProgramData\\Microsoft\\","dstpath":""}
{"ts":104703,"kind":"file","effect":"file_read","action":"open_read","pid":976,"procid":90,"srcpath":"C:\\ProgramData\\Microsoft","dstpath":""}
{"ts":104703,"kind":"file","effect":"file_read","action":"open_read","pid":976,"procid":90,"srcpath":"C:\\ProgramData\\Microsoft","dstpath":""}
{"ts":104703,"kind":"file","effect":"file_read","action":"open_read","pid":976,"procid":90,"srcpath":"C:\\ProgramData\\Microsoft\\","dstpath":""}
{"ts":104703,"kind":"file","effect":"file_read","action":"open_read","pid":976,"procid":90,"srcpath":"C:\\ProgramData","dstpath":""}
{"ts":104703,"kind":"file","effect":"file_read","action":"open_read","pid":976,"procid":90,"srcpath":"C:\\ProgramData\\","dstpath":""}
{"ts":104703,"kind":"file","effect":"file_read","action":"open_read","pid":976,"procid":90,"srcpath":"C:\\ProgramData","dstpath":""}
{"ts":104703,"kind":"file","effect":"file_read","action":"open_read","pid":976,"procid":90,"srcpath":"C:\\ProgramData","dstpath":""}
{"ts":104703,"kind":"file","effect":"file_read","action":"open_read","pid":976,"procid":90,"srcpath":"C:\\ProgramData\\","dstpath":""}
{"ts":104703,"kind":"file","effect":"file_read","action":"open_read","pid":976,"procid":90,"srcpath":"\\??\\C:","dstpath":""}
{"ts":104703,"kind":"file","effect":"file_read","action":"open_read","pid":976,"procid":90,"srcpath":"\\??\\MountPointManager","dstpath":""}
{"ts":104703,"kind":"file","effect":"file_read","action":"open_read","pid":976,"procid":90,"srcpath":"\\??\\C:","dstpath":""}
{"ts":104703,"kind":"file","effect":"file_read","action":"open_read","pid":976,"procid":90,"srcpath":"\\??\\MountPointManager","dstpath":""}
{"ts":104703,"kind":"file","effect":"file_read","action":"open_read","pid":976,"procid":90,"srcpath":"\\??\\Volume{301fc0b2-0000-0000-0000-d01200000000}","dstpath":""}
{"ts":104703,"kind":"file","effect":"file_read","action":"open_read","pid":976,"procid":90,"srcpath":"\\??\\PhysicalDrive0","dstpath":""}
{"ts":104703,"kind":"file","effect":"file_read","action":"open_read","pid":976,"procid":90,"srcpath":"C:\\ProgramData\\Microsoft\\Network\\Downloader\\qmgr.jfm","dstpath":""}
{"ts":104718,"kind":"file","effect":"file_written","action":"open_modify","pid":976,"procid":90,"srcpath":"C:\\ProgramData\\Microsoft\\Network\\Downloader\\qmgr.db","dstpath":""}
{"ts":104718,"kind":"file","effect":"file_written","action":"open_modify","pid":976,"procid":90,"srcpath":"C:\\ProgramData\\Microsoft\\Network\\Downloader\\qmgr.db","dstpath":""}
{"ts":104750,"kind":"file","effect":"file_read","action":"open_read","pid":976,"procid":90,"srcpath":"C:\\Windows","dstpath":""}
{"ts":104750,"kind":"file","effect":"file_read","action":"open_read","pid":976,"procid":90,"srcpath":"C:\\Windows","dstpath":""}
{"ts":104750,"kind":"file","effect":"file_read","action":"open_read","pid":976,"procid":90,"srcpath":"C:\\Windows","dstpath":""}
{"ts":104750,"kind":"file","effect":"file_read","action":"open_read","pid":976,"procid":90,"srcpath":"\\??\\C:","dstpath":""}
{"ts":104750,"kind":"file","effect":"file_read","action":"open_read","pid":976,"procid":90,"srcpath":"\\??\\MountPointManager","dstpath":""}
{"ts":104750,"kind":"file","effect":"file_read","action":"open_read","pid":976,"procid":90,"srcpath":"\\??\\C:","dstpath":""}
{"ts":104750,"kind":"file","effect":"file_read","action":"open_read","pid":976,"procid":90,"srcpath":"\\??\\MountPointManager","dstpath":""}
{"ts":104750,"kind":"file","effect":"file_read","action":"open_read","pid":976,"procid":90,"srcpath":"\\??\\Volume{301fc0b2-0000-0000-0000-d01200000000}","dstpath":""}
{"ts":104750,"kind":"file","effect":"file_read","action":"open_read","pid":976,"procid":90,"srcpath":"\\??\\PhysicalDrive0","dstpath":""}
{"ts":104750,"kind":"file","effect":"file_written","action":"open_modify","pid":976,"procid":90,"srcpath":"C:\\Windows\\Debug\\ESE.TXT","dstpath":""}
{"ts":104781,"kind":"file","effect":"file_written","action":"open_modify","pid":976,"procid":90,"srcpath":"\\??\\PIPE\\lsarpc","dstpath":""}
{"ts":104781,"kind":"file","effect":"file_written","action":"open_modify","pid":976,"procid":90,"srcpath":"\\Device\\KsecDD","dstpath":""}
{"ts":104781,"kind":"file","effect":"file_written","action":"open_modify","pid":976,"procid":90,"srcpath":"\\??\\PIPE\\wkssvc","dstpath":""}
{"ts":104812,"kind":"file","effect":"file_written","action":"open_modify","pid":976,"procid":90,"srcpath":"\\Device\\Afd\\Endpoint","dstpath":""}
{"ts":104812,"kind":"file","effect":"file_read","action":"open_read","pid":976,"procid":90,"srcpath":"\\??\\Nsi","dstpath":""}
{"ts":104812,"kind":"file","effect":"file_written","action":"open_modify","pid":976,"procid":90,"srcpath":"\\Device\\Afd\\Endpoint","dstpath":""}
{"ts":104812,"kind":"file","effect":"file_written","action":"open_modify","pid":976,"procid":90,"srcpath":"\\Device\\Afd\\Endpoint","dstpath":""}
{"ts":104812,"kind":"file","effect":"file_written","action":"open_modify","pid":976,"procid":90,"srcpath":"\\Device\\Afd\\Endpoint","dstpath":""}
{"ts":104812,"kind":"file","effect":"file_written","action":"open_modify","pid":976,"procid":90,"srcpath":"\\Device\\Afd\\Endpoint","dstpath":""}
{"ts":104812,"kind":"file","effect":"file_written","action":"open_modify","pid":976,"procid":90,"srcpath":"\\Device\\RasAcd","dstpath":""}
{"ts":104812,"kind":"file","effect":"file_written","action":"open_modify","pid":976,"procid":90,"srcpath":"\\Device\\Afd\\Endpoint","dstpath":""}
{"ts":104812,"kind":"file","effect":"file_written","action":"open_modify","pid":976,"procid":90,"srcpath":"\\Device\\Afd\\Endpoint","dstpath":""}
{"ts":104906,"kind":"file","effect":"file_read","action":"Unknown","pid":4668,"procid":93,"srcpath":"C:\\Windows\\system32\\","dstpath":""}
{"ts":104921,"kind":"file","effect":"file_read","action":"open_read","pid":4668,"procid":93,"srcpath":"\\Device\\CNG","dstpath":""}
{"ts":104984,"kind":"file","effect":"file_written","action":"open_modify","pid":4668,"procid":93,"srcpath":"\\Device\\KsecDD","dstpath":""}
{"ts":105000,"kind":"file","effect":"file_read","action":"open_read","pid":4668,"procid":93,"srcpath":"C:\\ProgramData\\microsoft\\IdentityCRL\\production\\ppcrlconfig600.dll","dstpath":""}
{"ts":105000,"kind":"file","effect":"file_read","action":"open_read","pid":4668,"procid":93,"srcpath":"C:\\ProgramData\\microsoft\\IdentityCRL\\production\\ppcrlconfig600.dll","dstpath":""}
{"ts":105000,"kind":"file","effect":"file_read","action":"open_read","pid":4668,"procid":93,"srcpath":"C:\\ProgramData\\microsoft\\IdentityCRL\\production\\ppcrlconfig600.dll","dstpath":""}
{"ts":105000,"kind":"file","effect":"file_read","action":"open_read","pid":4668,"procid":93,"srcpath":"C:\\ProgramData\\microsoft\\IdentityCRL\\production\\ppcrlconfig600.dll","dstpath":""}
{"ts":105000,"kind":"file","effect":"file_read","action":"open_read","pid":4668,"procid":93,"srcpath":"C:\\ProgramData\\microsoft\\IdentityCRL\\production\\ppcrlconfig600.dll","dstpath":""}
{"ts":105000,"kind":"file","effect":"file_read","action":"open_read","pid":4668,"procid":93,"srcpath":"C:\\ProgramData\\microsoft\\IdentityCRL\\production\\ppcrlconfig600.dll","dstpath":""}
{"ts":105000,"kind":"file","effect":"file_read","action":"open_read","pid":4668,"procid":93,"srcpath":"C:\\ProgramData\\microsoft\\IdentityCRL\\production\\ppcrlconfig600.dll","dstpath":""}
{"ts":105015,"kind":"file","effect":"file_read","action":"open_read","pid":4668,"procid":93,"srcpath":"\\??\\Nsi","dstpath":""}
{"ts":105062,"kind":"file","effect":"file_read","action":"Unknown","pid":4448,"procid":94,"srcpath":"C:\\Windows\\system32\\","dstpath":""}
{"ts":105093,"kind":"file","effect":"file_read","action":"open_read","pid":4448,"procid":94,"srcpath":"\\Device\\CNG","dstpath":""}
{"ts":105187,"kind":"file","effect":"file_read","action":"open_read","pid":4448,"procid":94,"srcpath":"C:\\ProgramData\\Microsoft\\Windows\\ClipSvc\\tokens.dat","dstpath":""}
{"ts":105187,"kind":"file","effect":"file_read","action":"Unknown","pid":4448,"procid":94,"srcpath":"C:\\ProgramData\\Microsoft\\Windows\\ClipSvc\\GenuineTicket\\","dstpath":""}
{"ts":105203,"kind":"file","effect":"file_read","action":"Unknown","pid":4448,"procid":94,"srcpath":"C:\\ProgramData\\Microsoft\\Windows\\ClipSvc\\Import\\","dstpath":""}
{"ts":105203,"kind":"file","effect":"file_read","action":"Unknown","pid":4448,"procid":94,"srcpath":"C:\\ProgramData\\Microsoft\\Windows\\ClipSvc\\Install\\KeyHolder\\","dstpath":""}
{"ts":105203,"kind":"file","effect":"file_read","action":"Unknown","pid":4448,"procid":94,"srcpath":"C:\\ProgramData\\Microsoft\\Windows\\ClipSvc\\Install\\Device\\","dstpath":""}
{"ts":105203,"kind":"file","effect":"file_read","action":"Unknown","pid":4448,"procid":94,"srcpath":"C:\\ProgramData\\Microsoft\\Windows\\ClipSvc\\Install\\Migration\\","dstpath":""}
{"ts":105203,"kind":"file","effect":"file_read","action":"Unknown","pid":4448,"procid":94,"srcpath":"C:\\ProgramData\\Microsoft\\Windows\\ClipSvc\\Install\\Apps\\","dstpath":""}
{"ts":105203,"kind":"file","effect":"file_written","action":"open_modify","pid":4448,"procid":94,"srcpath":"\\??\\TPM","dstpath":""}
{"ts":105203,"kind":"file","effect":"file_written","action":"open_modify","pid":4448,"procid":94,"srcpath":"\\Device\\KsecDD","dstpath":""}
{"ts":105250,"kind":"file","effect":"file_read","action":"open_read","pid":4668,"procid":93,"srcpath":"\\Device\\KsecDD","dstpath":""}
{"ts":105312,"kind":"file","effect":"file_written","action":"open_modify","pid":4448,"procid":94,"srcpath":"\\??\\TPM","dstpath":""}
{"ts":105328,"kind":"file","effect":"file_written","action":"open_modify","pid":4448,"procid":94,"srcpath":"\\??\\TPM","dstpath":""}
{"ts":105343,"kind":"file","effect":"file_written","action":"open_modify","pid":4448,"procid":94,"srcpath":"\\??\\TPM","dstpath":""}
{"ts":105843,"kind":"file","effect":"file_written","action":"open_modify","pid":976,"procid":90,"srcpath":"\\Device\\Afd\\Endpoint","dstpath":""}
{"ts":106859,"kind":"file","effect":"file_written","action":"open_modify","pid":976,"procid":90,"srcpath":"\\Device\\Afd\\Endpoint","dstpath":""}
{"ts":106859,"kind":"file","effect":"file_written","action":"open_modify","pid":976,"procid":90,"srcpath":"\\Device\\Afd\\Endpoint","dstpath":""}
{"ts":106937,"kind":"file","effect":"file_read","action":"open_read","pid":976,"procid":90,"srcpath":"\\Device\\DeviceApi\\CMApi","dstpath":""}
{"ts":106937,"kind":"file","effect":"file_read","action":"open_read","pid":976,"procid":90,"srcpath":"C:\\Windows\\ServiceProfiles\\LocalService\\AppData\\Local\\FontCache\\Fonts","dstpath":""}
{"ts":106937,"kind":"file","effect":"file_read","action":"open_read","pid":976,"procid":90,"srcpath":"C:\\Windows\\ServiceProfiles\\LocalService\\AppData\\Local\\FontCache","dstpath":""}
{"ts":106937,"kind":"file","effect":"file_read","action":"open_read","pid":976,"procid":90,"srcpath":"C:\\Windows\\ServiceProfiles\\LocalService\\AppData\\Local","dstpath":""}
{"ts":106937,"kind":"file","effect":"file_read","action":"open_read","pid":976,"procid":90,"srcpath":"C:\\Windows\\ServiceProfiles\\LocalService\\AppData","dstpath":""}
{"ts":106937,"kind":"file","effect":"file_read","action":"open_read","pid":976,"procid":90,"srcpath":"C:\\Windows\\ServiceProfiles\\LocalService","dstpath":""}
{"ts":106937,"kind":"file","effect":"file_read","action":"open_read","pid":976,"procid":90,"srcpath":"C:\\Windows\\ServiceProfiles","dstpath":""}
{"ts":106937,"kind":"file","effect":"file_read","action":"open_read","pid":976,"procid":90,"srcpath":"C:\\Windows","dstpath":""}
{"ts":106937,"kind":"file","effect":"file_read","action":"open_read","pid":976,"procid":90,"srcpath":"C:\\Windows","dstpath":""}
{"ts":106937,"kind":"file","effect":"file_read","action":"open_read","pid":976,"procid":90,"srcpath":"C:\\Windows","dstpath":""}
{"ts":106937,"kind":"file","effect":"file_read","action":"open_read","pid":976,"procid":90,"srcpath":"\\??\\C:","dstpath":""}
{"ts":106937,"kind":"file","effect":"file_read","action":"open_read","pid":976,"procid":90,"srcpath":"\\??\\C:","dstpath":""}
{"ts":106937,"kind":"file","effect":"file_read","action":"open_read","pid":976,"procid":90,"srcpath":"\\??\\MountPointManager","dstpath":""}
{"ts":106937,"kind":"file","effect":"file_read","action":"open_read","pid":976,"procid":90,"srcpath":"\\??\\C:","dstpath":""}
{"ts":106937,"kind":"file","effect":"file_read","action":"open_read","pid":976,"procid":90,"srcpath":"\\??\\C:","dstpath":""}
{"ts":106937,"kind":"file","effect":"file_read","action":"open_read","pid":976,"procid":90,"srcpath":"\\??\\C:","dstpath":""}
{"ts":106937,"kind":"file","effect":"file_read","action":"open_read","pid":976,"procid":90,"srcpath":"\\??\\MountPointManager","dstpath":""}
{"ts":106937,"kind":"file","effect":"file_read","action":"Unknown","pid":976,"procid":90,"srcpath":"\\??\\Volume{301fc0b2-0000-0000-0000-d01200000000}\\","dstpath":""}
{"ts":106937,"kind":"file","effect":"file_written","action":"open_modify","pid":976,"procid":90,"srcpath":"C:\\Windows\\ServiceProfiles\\LocalService\\AppData\\Local\\FontCache\\Fonts\\Download-1.tmp","dstpath":""}
{"ts":106937,"kind":"file","effect":"file_read","action":"open_read","pid":976,"procid":90,"srcpath":"\\DEVICE\\NETBT_TCPIP_{B6098F25-97F6-4D7D-BAE2-D21D794F77F5}","dstpath":""}
{"ts":106937,"kind":"file","effect":"file_read","action":"open_read","pid":976,"procid":90,"srcpath":"\\DEVICE\\NETBT_TCPIP_{ACBF57ED-C3BF-11EF-A098-806E6F6E6963}","dstpath":""}
{"ts":106937,"kind":"file","effect":"file_read","action":"open_read","pid":976,"procid":90,"srcpath":"\\DEVICE\\NETBT_TCPIP_{B6098F25-97F6-4D7D-BAE2-D21D794F77F5}","dstpath":""}
{"ts":106937,"kind":"file","effect":"file_read","action":"open_read","pid":976,"procid":90,"srcpath":"\\DEVICE\\NETBT_TCPIP_{ACBF57ED-C3BF-11EF-A098-806E6F6E6963}","dstpath":""}
{"ts":106953,"kind":"file","effect":"file_read","action":"open_read","pid":976,"procid":90,"srcpath":"\\DEVICE\\NETBT_TCPIP_{B6098F25-97F6-4D7D-BAE2-D21D794F77F5}","dstpath":""}
{"ts":106953,"kind":"file","effect":"file_read","action":"open_read","pid":976,"procid":90,"srcpath":"\\DEVICE\\NETBT_TCPIP_{ACBF57ED-C3BF-11EF-A098-806E6F6E6963}","dstpath":""}
{"ts":106953,"kind":"file","effect":"file_written","action":"open_modify","pid":976,"procid":90,"srcpath":"\\Device\\Afd\\Endpoint","dstpath":""}
{"ts":106953,"kind":"file","effect":"file_written","action":"open_modify","pid":976,"procid":90,"srcpath":"\\Device\\Afd\\Endpoint","dstpath":""}
{"ts":106953,"kind":"file","effect":"file_written","action":"open_modify","pid":976,"procid":90,"srcpath":"\\Device\\RasAcd","dstpath":""}
{"ts":119000,"kind":"file","effect":"file_written","action":"open_modify","pid":976,"procid":90,"srcpath":"\\Device\\Afd\\Endpoint","dstpath":""}
