{"analysis_id": "20241229-C5G5QF", "score": 0, "signatures": [], "target": {"filename": "wic_x64_enu.exe", "orig_filename": "wic_x64_enu.exe", "platforms": [{"platform": "windows", "os_version": ""}], "size": 1911592, "filetype": "PE32 executable (GUI) Intel 80386, for MS Windows", "media_type": "application/x-dosexec", "extrpath": [], "password": "", "machine_tags": [], "container": false, "sha512": "0123bbbbcf89ba49baf2b6a48df916cd2ed0dab27230c48ae140ac632a0d37f62108a510e9bed297bb072f9869d3cd401f31e1307249735c9238da80a703b649", "sha256": "5822fecd69a90c2833965a25e8779000825d69cc8c9250933f0ab70df52171e1", "sha1": "4bdbf76a7bc96453306c893b4a7b2b8ae6127f67", "md5": "2eb787be1deb373efc259d1f42146419"}, "category": "file", "ttps": [], "tags": [], "families": [], "platforms": [], "virustotal": {}, "static": {"pe": {"peid_signatures": ["MS SFX CAB Archive file"], "pe_imports": [{"dll": "KERNEL32.dll", "imports": [{"address": "0x100203c", "name": "GetDriveTypeA"}, {"address": "0x1002040", "name": "HeapFree"}, {"address": "0x1002044", "name": "FormatMessageA"}, {"address": "0x1002048", "name": "LeaveCriticalSection"}, {"address": "0x100204c", "name": "DeleteFileA"}, {"address": "0x1002050", "name": "EnterCriticalSection"}, {"address": "0x1002054", "name": "TerminateProcess"}, {"address": "0x1002058", "name": "WaitForMultipleObjects"}, {"address": "0x100205c", "name": "CreateEventW"}, {"address": "0x1002060", "name": "SetEvent"}, {"address": "0x1002064", "name": "Sleep"}, {"address": "0x1002068", "name": "SetEnvironmentVariableA"}, {"address": "0x100206c", "name": "GetEnvironmentVariableA"}, {"address": "0x1002070", "name": "WideCharToMultiByte"}, {"address": "0x1002074", "name": "HeapAlloc"}, {"address": "0x1002078", "name": "SetLastError"}, {"address": "0x100207c", "name": "WriteFile"}, {"address": "0x1002080", "name": "MoveFileA"}, {"address": "0x1002084", "name": "ExitProcess"}, {"address": "0x1002088", "name": "DeleteCriticalSection"}, {"address": "0x100208c", "name": "FlushFileBuffers"}, {"address": "0x1002090", "name": "GetVersionExA"}, {"address": "0x1002094", "name": "WaitForSingleObject"}, {"address": "0x1002098", "name": "OpenEventA"}, {"address": "0x100209c", "name": "GetCurrentProcess"}, {"address": "0x10020a0", "name": "GetFileAttributesA"}, {"address": "0x10020a4", "name": "GetCommandLineA"}, {"address": "0x10020a8", "name": "GetModuleFileNameA"}, {"address": "0x10020ac", "name": "CreateFileA"}, {"address": "0x10020b0", "name": "FindNextFileA"}, {"address": "0x10020b4", "name": "FindFirstFileA"}, {"address": "0x10020b8", "name": "CopyFileA"}, {"address": "0x10020bc", "name": "SetFileAttributesA"}, {"address": "0x10020c0", "name": "SystemTimeToFileTime"}, {"address": "0x10020c4", "name": "GetSystemTime"}, {"address": "0x10020c8", "name": "GetDiskFreeSpaceA"}, {"address": "0x10020cc", "name": "QueryDosDeviceA"}, {"address": "0x10020d0", "name": "GetCurrentDirectoryA"}, {"address": "0x10020d4", "name": "SetEndOfFile"}, {"address": "0x10020d8", "name": "SetFileTime"}, {"address": "0x10020dc", "name": "LocalFileTimeToFileTime"}, {"address": "0x10020e0", "name": "DosDateTimeToFileTime"}, {"address": "0x10020e4", "name": "GetExitCodeProcess"}, {"address": "0x10020e8", "name": "CreateProcessA"}, {"address": "0x10020ec", "name": "ExpandEnvironmentStringsA"}, {"address": "0x10020f0", "name": "GetFileSize"}, {"address": "0x10020f4", "name": "CreateThread"}, {"address": "0x10020f8", "name": "CreateEventA"}, {"address": "0x10020fc", "name": "GetProcessHeap"}, {"address": "0x1002100", "name": "InitializeCriticalSectionAndSpinCount"}, {"address": "0x1002104", "name": "GetModuleHandleA"}, {"address": "0x1002108", "name": "QueryPerformanceCounter"}, {"address": "0x100210c", "name": "GetCurrentThreadId"}, {"address": "0x1002110", "name": "GetCurrentProcessId"}, {"address": "0x1002114", "name": "GetSystemTimeAsFileTime"}, {"address": "0x1002118", "name": "SetUnhandledExceptionFilter"}, {"address": "0x100211c", "name": "CloseHandle"}, {"address": "0x1002120", "name": "DeviceIoControl"}, {"address": "0x1002124", "name": "GetSystemDirectoryA"}, {"address": "0x1002128", "name": "LoadLibraryA"}, {"address": "0x100212c", "name": "GetProcAddress"}, {"address": "0x1002130", "name": "FreeLibrary"}, {"address": "0x1002134", "name": "SetErrorMode"}, {"address": "0x1002138", "name": "GetTickCount"}, {"address": "0x100213c", "name": "CreateDirectoryA"}, {"address": "0x1002140", "name": "GetLastError"}, {"address": "0x1002144", "name": "RemoveDirectoryA"}, {"address": "0x1002148", "name": "MoveFileExA"}, {"address": "0x100214c", "name": "SetFilePointer"}, {"address": "0x1002150", "name": "FindClose"}, {"address": "0x1002154", "name": "ReadFile"}]}, {"dll": "msvcrt.dll", "imports": [{"address": "0x100218c", "name": "strchr"}, {"address": "0x1002190", "name": "_strnicmp"}, {"address": "0x1002194", "name": "_stricmp"}, {"address": "0x1002198", "name": "strrchr"}, {"address": "0x100219c", "name": "_strlwr"}, {"address": "0x10021a0", "name": "strncpy"}, {"address": "0x10021a4", "name": "strstr"}, {"address": "0x10021a8", "name": "_snprintf"}, {"address": "0x10021ac", "name": "sprintf"}]}, {"dll": "ADVAPI32.dll", "imports": [{"address": "0x1002000", "name": "AllocateAndInitializeSid"}, {"address": "0x1002004", "name": "GetTokenInformation"}, {"address": "0x1002008", "name": "GetLengthSid"}, {"address": "0x100200c", "name": "InitiateSystemShutdownA"}, {"address": "0x1002010", "name": "CryptReleaseContext"}, {"address": "0x1002014", "name": "CryptGenRandom"}, {"address": "0x1002018", "name": "CryptAcquireContextA"}, {"address": "0x100201c", "name": "SetSecurityDescriptorDacl"}, {"address": "0x1002020", "name": "AddAccessAllowedAce"}, {"address": "0x1002024", "name": "InitializeAcl"}, {"address": "0x1002028", "name": "InitializeSecurityDescriptor"}, {"address": "0x100202c", "name": "OpenProcessToken"}]}, {"dll": "USER32.dll", "imports": [{"address": "0x1002168", "name": "ShowWindow"}, {"address": "0x100216c", "name": "SendDlgItemMessageA"}, {"address": "0x1002170", "name": "SendMessageA"}, {"address": "0x1002174", "name": "DialogBoxParamA"}, {"address": "0x1002178", "name": "LoadStringA"}, {"address": "0x100217c", "name": "EndDialog"}, {"address": "0x1002180", "name": "SetParent"}, {"address": "0x1002184", "name": "MessageBoxA"}]}, {"dll": "ntdll.dll", "imports": [{"address": "0x10021b4", "name": "NtShutdownSystem"}, {"address": "0x10021b8", "name": "NtAdjustPrivilegesToken"}, {"address": "0x10021bc", "name": "NtClose"}, {"address": "0x10021c0", "name": "NtOpenProcessToken"}]}, {"dll": "COMCTL32.dll", "imports": [{"address": "0x1002034", "name": ""}]}, {"dll": "SHELL32.dll", "imports": [{"address": "0x100215c", "name": "SHBrowseForFolderA"}, {"address": "0x1002160", "name": "SHGetPathFromIDListA"}]}], "pe_exports": [], "pe_sections": [{"name": ".text", "virtual_address": "0x00002000", "virtual_size": "0x000078a0", "size_of_data": "0x00007a00", "entropy": 6.583408467837293}, {"name": ".data", "virtual_address": "0x0000a000", "virtual_size": "0x000110d4", "size_of_data": "0x00000200", "entropy": 0.5134905185915475}, {"name": ".rsrc", "virtual_address": "0x0001c000", "virtual_size": "0x00000988", "size_of_data": "0x001c9000", "entropy": 7.99958076498258}], "pe_resources": [{"name": "RT_DIALOG", "offset": "0x0001c4a8", "size": "0x0000011a", "filetype": "data", "language": "LANG_ENGLISH", "sublanguage": "SUBLANG_ENGLISH_US"}, {"name": "RT_DIALOG", "offset": "0x0001c5c8", "size": "0x000000e0", "filetype": "data", "language": "LANG_ENGLISH", "sublanguage": "SUBLANG_ENGLISH_US"}, {"name": "RT_STRING", "offset": "0x0001c6a8", "size": "0x000002da", "filetype": "data", "language": "LANG_ENGLISH", "sublanguage": "SUBLANG_ENGLISH_US"}, {"name": "RT_VERSION", "offset": "0x0001c120", "size": "0x00000388", "filetype": "data", "language": "LANG_ENGLISH", "sublanguage": "SUBLANG_ENGLISH_US"}], "pe_versioninfo": [{"name": "CompanyName", "value": "Microsoft Corporation"}, {"name": "FileDescription", "value": "Self-Extracting Cabinet"}, {"name": "FileVersion", "value": "6.1.0022.4 (SRV03_QFE.031113-0918)"}, {"name": "InternalName", "value": "SFXCAB.EXE"}, {"name": "LegalCopyright", "value": "\u00a9 Microsoft Corporation. All rights reserved."}, {"name": "OriginalFilename", "value": "SFXCAB.EXE"}, {"name": "ProductName", "value": "Microsoft\u00ae Windows\u00ae Operating System"}, {"name": "ProductVersion", "value": "6.1.0022.4"}, {"name": "Translation", "value": "0x0409 0x04b0"}], "pe_imphash": "092eb6daba2f17cbda102fd1a32acd00", "pe_timestamp": "2005-02-25T06:44:38", "signatures": [{"md5": "6823267ab35ec7a5449904bb4d8041a7", "sha1": "f46ac0c6efbb8c6a14f55f09e2d37df4c0de012d", "sha256": "1c1983300c10fb262c0b2304b7be15aaba10ae356ebbbb177583dc44774eb080", "sha512": "1c1983300c10fb262c0b2304b7be15aaba10ae356ebbbb177583dc44774eb080", "serial_number": "95367435335131489231313444090147582372", "subject": {"countryName": "US", "organizationName": "VeriSign, Inc.", "commonName": "VeriSign Time Stamping Services CA"}, "issuer": {"countryName": "ZA", "stateOrProvinceName": "Western Cape", "localityName": "Durbanville", "organizationName": "Thawte", "organizationalUnitName": "Thawte Certification", "commonName": "Thawte Timestamping CA"}, "extensions": {"authorityInfoAccess": {"OCSP": "http://ocsp.verisign.com"}, "cRLDistributionPoints": ["http://crl.verisign.com/ThawteTimestampingCA.crl"], "extendedKeyUsage": ["timeStamping"], "keyUsage": {"digital_signature": false, "content_commitment": false, "key_encipherment": false, "data_encipherment": false, "key_agreement": false, "key_cert_sign": true, "crl_sign": true}, "subjectAltName": ["TSA2048-1-53"]}}, {"md5": "5340e91a17595750554527215846ee71", "sha1": "817e78267300cb0fe5d631357851db366123a690", "sha256": "2ade3fa71fa82fed7022b48b5c6dbace27ea4c48b9bfd98db84ee13f7b706fb6", "sha512": "2ade3fa71fa82fed7022b48b5c6dbace27ea4c48b9bfd98db84ee13f7b706fb6", "serial_number": "18490660337486627817154717305594869384", "subject": {"countryName": "US", "organizationName": "VeriSign, Inc.", "commonName": "VeriSign Time Stamping Services Signer"}, "issuer": {"countryName": "US", "organizationName": "VeriSign, Inc.", "commonName": "VeriSign Time Stamping Services CA"}, "extensions": {"authorityInfoAccess": {"OCSP": "http://ocsp.verisign.com"}, "cRLDistributionPoints": ["http://crl.verisign.com/tss-ca.crl"], "extendedKeyUsage": ["timeStamping"], "keyUsage": {"digital_signature": true, "content_commitment": true, "key_encipherment": false, "data_encipherment": false, "key_agreement": false, "key_cert_sign": false, "crl_sign": false}, "subjectAltName": ["TSA2048-1-54"]}}, {"md5": "2a954eca79b2874573d92d90baf99fb6", "sha1": "a43489159a520f0d93d032ccaf37e7fe20a8b419", "sha256": "f38406e540d7a9d90cb4a9479299640ffb6df9e224ecc7a01c0d9558d8dad77d", "sha512": "f38406e540d7a9d90cb4a9479299640ffb6df9e224ecc7a01c0d9558d8dad77d", "serial_number": "3914548144742538765706922673626944", "subject": {"organizationalUnitName": "Microsoft Corporation", "commonName": "Microsoft Root Authority"}, "issuer": {"organizationalUnitName": "Microsoft Corporation", "commonName": "Microsoft Root Authority"}, "extensions": {}}, {"md5": "90c0f7b4b26ee553f4bd0dad3f58520d", "sha1": "d07ea64088a80085f01bd40aa4ead82f470482a6", "sha256": "6a3c4d89cd6297023831b9c4f718ce71cf8753a2be49e021245ec6ba5066ff00", "sha512": "6a3c4d89cd6297023831b9c4f718ce71cf8753a2be49e021245ec6ba5066ff00", "serial_number": "140958392345760424954180966847103772602", "subject": {"countryName": "US", "stateOrProvinceName": "Washington", "localityName": "Redmond", "organizationName": "Microsoft Corporation", "organizationalUnitName": "Copyright (c) 2000 Microsoft Corp.", "commonName": "Microsoft Code Signing PCA"}, "issuer": {"organizationalUnitName": "Microsoft Corporation", "commonName": "Microsoft Root Authority"}, "extensions": {"extendedKeyUsage": ["codeSigning"], "subjectKeyIdentifier": "JfgrS13IclSt5fagKhcW+8H5U4E=", "keyUsage": {"digital_signature": false, "content_commitment": true, "key_encipherment": false, "data_encipherment": false, "key_agreement": false, "key_cert_sign": true, "crl_sign": true}}}, {"md5": "5fc18a70cd3f8950d5d7ac668e804a71", "sha1": "564e01066387f26c912010d06bd78d3cf1e845ab", "sha256": "31a6d7325c3861ba092bc5d3d25a7d4fef62ebf9a3490f65897b87623ecc1295", "sha512": "31a6d7325c3861ba092bc5d3d25a7d4fef62ebf9a3490f65897b87623ecc1295", "serial_number": "459372263162810699087973", "subject": {"countryName": "US", "stateOrProvinceName": "Washington", "localityName": "Redmond", "organizationName": "Microsoft Corporation", "commonName": "Microsoft Corporation"}, "issuer": {"countryName": "US", "stateOrProvinceName": "Washington", "localityName": "Redmond", "organizationName": "Microsoft Corporation", "organizationalUnitName": "Copyright (c) 2000 Microsoft Corp.", "commonName": "Microsoft Code Signing PCA"}, "extensions": {"keyUsage": {"digital_signature": true, "content_commitment": true, "key_encipherment": false, "data_encipherment": false, "key_agreement": false, "key_cert_sign": false, "crl_sign": false}, "subjectKeyIdentifier": "7tlrqXVTzU/uG04ZBh6jnKvPlP0=", "extendedKeyUsage": ["codeSigning"], "authorityKeyIdentifier": "JfgrS13IclSt5fagKhcW+8H5U4E=", "cRLDistributionPoints": ["http://crl.microsoft.com/pki/crl/products/CodeSignPCA2.crl"], "authorityInfoAccess": {"caIssuers": "http://www.microsoft.com/pki/certs/CodeSignPCA2.crt"}}}]}}, "command": {}, "errors": {}}