{"analysis_id": "20241227-8T9PM3", "score": 0, "signatures": [], "target": {"filename": "VirusShare_7f445026b5b4929879760baf43e6c15b.exe", "orig_filename": "VirusShare_7f445026b5b4929879760baf43e6c15b", "platforms": [{"platform": "windows", "os_version": ""}], "size": 196608, "filetype": "PE32 executable (GUI) Intel 80386, for MS Windows", "media_type": "application/x-dosexec", "extrpath": [], "password": "", "machine_tags": [], "container": false, "sha512": "1d5caa95f081353bf59f5e82d93debb7339178767385995d6b4c9b87bc481e172ee512dcd9ba6a94750eb4b40e3a64ea50c696e7e55205f809bcb2cfad18b0fe", "sha256": "bde7b2fc0a2c63d068a0f5b304c7c773ceca0b470250b98b1ce1a07b0e5cb1de", "sha1": "6b79b8a0b28b93506e8e2f66a28099578b260b3b", "md5": "7f445026b5b4929879760baf43e6c15b"}, "category": "file", "ttps": [], "tags": [], "families": [], "platforms": [], "virustotal": {}, "static": {"pe": {"peid_signatures": ["Borland Delphi 3.0 (???)"], "pe_imports": [{"dll": "SHLWAPI.dll", "imports": [{"address": "0x408000", "name": "PathIsUNCA"}]}, {"dll": "KERNEL32.dll", "imports": [{"address": "0x408008", "name": "LocalAlloc"}]}, {"dll": "USER32.dll", "imports": [{"address": "0x408010", "name": "VkKeyScanW"}]}], "pe_exports": [], "pe_sections": [{"name": ".text", "virtual_address": "0x00001000", "virtual_size": "0x00006e46", "size_of_data": "0x00007000", "entropy": 7.060266069476784}, {"name": "rt_ecx", "virtual_address": "0x00008000", "virtual_size": "0x00000018", "size_of_data": "0x00000200", "entropy": 0.1129889916064758}, {"name": "rt_eax", "virtual_address": "0x00009000", "virtual_size": "0x000000b8", "size_of_data": "0x00000200", "entropy": 1.5661538847063778}, {"name": "rt_esp", "virtual_address": "0x0000a000", "virtual_size": "0x0000001c", "size_of_data": "0x00000200", "entropy": 0.16299007530476972}, {"name": "rt_edx", "virtual_address": "0x0000b000", "virtual_size": "0x00000036", "size_of_data": "0x00000200", "entropy": 0.9526114362570663}, {"name": "rt_ebx", "virtual_address": "0x0000c000", "virtual_size": "0x00009b7e", "size_of_data": "0x00009c00", "entropy": 6.8266862877196814}, {"name": ".data", "virtual_address": "0x00016000", "virtual_size": "0x000334d6", "size_of_data": "0x00000c00", "entropy": 4.359380593089205}, {"name": ".rsrc", "virtual_address": "0x0004a000", "virtual_size": "0x0001d3b0", "size_of_data": "0x0001d400", "entropy": 6.831228690001239}, {"name": ".reloc", "virtual_address": "0x00068000", "virtual_size": "0x00000774", "size_of_data": "0x00000800", "entropy": 6.506820806163709}], "pe_resources": [{"name": "RT_ICON", "offset": "0x00066740", "size": "0x00000128", "filetype": "Device independent bitmap graphic, 16 x 32 x 4, 303174162 compression, image size 303174290, resolution 303174162 x 303174162 px/m, 303174162 important colors", "language": "LANG_ENGLISH", "sublanguage": "SUBLANG_ENGLISH_US"}, {"name": "RT_ICON", "offset": "0x00066868", "size": "0x00000106", "filetype": "Device independent bitmap graphic, 32 x 64 x 4, 151587081 compression, image size 151587593, resolution 151587081 x 151587081 px/m, 151587081 important colors", "language": "LANG_ENGLISH", "sublanguage": "SUBLANG_ENGLISH_US"}, {"name": "RT_ICON", "offset": "0x0006696e", "size": "0x00000128", "filetype": "Device independent bitmap graphic, 16 x 32 x 4, 168430090 compression, image size 168430218, resolution 168430090 x 168430090 px/m, 168430090 important colors", "language": "LANG_ENGLISH", "sublanguage": "SUBLANG_ENGLISH_US"}, {"name": "RT_ICON", "offset": "0x00066a96", "size": "0x00000128", "filetype": "Device independent bitmap graphic, 16 x 32 x 4, 84215045 compression, image size 84215173, resolution 84215045 x 84215045 px/m, 84215045 important colors", "language": "LANG_ENGLISH", "sublanguage": "SUBLANG_ENGLISH_US"}, {"name": "RT_GROUP_ICON", "offset": "0x00066bbe", "size": "0x00000092", "filetype": "data", "language": "LANG_ENGLISH", "sublanguage": "SUBLANG_ENGLISH_US"}, {"name": "RT_VERSION", "offset": "0x00066c50", "size": "0xffff0360", "filetype": "data", "language": "LANG_ENGLISH", "sublanguage": "SUBLANG_ENGLISH_US"}], "pe_versioninfo": [{"name": "CompanyName", "value": "Microsoft Corporation"}, {"name": "FileDescription", "value": "DRMv2 Client DLL"}, {"name": "FileVersion", "value": "11.0.7600.16385"}, {"name": "InternalName", "value": "drmv2clt.dll"}, {"name": "LegalCopyright", "value": "\u00a9 Microsoft Corporation. All rights reserved."}, {"name": "OriginalFilename", "value": "drmv2clt.dll"}, {"name": "ProductName", "value": "Microsoft\u00ae DRM"}, {"name": "ProductVersion", "value": "11.0.7600.16385"}, {"name": "OLESelfRegister", "value": ""}, {"name": "Translation", "value": "0x0409 0x04b0"}], "pe_imphash": "1b52c2d4d3a540d0a2193938c9f18867", "pe_timestamp": "2011-03-26T18:06:26", "signatures": []}}, "command": {}, "errors": {}}